dis_bg_remover/__init__.py
dis_bg_remover/remover.py
dis_bg_remover-0.1.2.dist-info/LICENSE
dis_bg_remover-0.1.2.dist-info/METADATA
dis_bg_remover-0.1.2.dist-info/WHEEL
dis_bg_remover-0.1.2.dist-info/top_level.txt
dis_bg_remover-0.1.2.dist-info/RECORD
