Metadata-Version: 2.1
Name: dis-bg-remover
Version: 0.1.2
Summary: Highly Accurate Dichotomous Image Segmentation
Author: Amit
Author-email: amit@pulpdata.com.au
License-File: LICENSE
Requires-Dist: numpy
Requires-Dist: opencv-python
Requires-Dist: onnxruntime
